pikanetwork/__init__.py
pikanetwork/api.py
pikanetwork/builders.py
pikanetwork/exceptions.py
pikanetwork/models.py
pikanetwork.py-1.0.2.dist-info/LICENSE
pikanetwork.py-1.0.2.dist-info/METADATA
pikanetwork.py-1.0.2.dist-info/WHEEL
pikanetwork.py-1.0.2.dist-info/top_level.txt
pikanetwork.py-1.0.2.dist-info/RECORD
